financedatabase/Cryptos.py
financedatabase/Currencies.py
financedatabase/ETFs.py
financedatabase/Equities.py
financedatabase/Funds.py
financedatabase/Indices.py
financedatabase/Moneymarkets.py
financedatabase/__init__.py
financedatabase/helpers.py
financedatabase-2.3.1.dist-info/LICENSE
financedatabase-2.3.1.dist-info/METADATA
financedatabase-2.3.1.dist-info/WHEEL
financedatabase-2.3.1.dist-info/RECORD
