Metadata-Version: 2.1
Name: financedatabase
Version: 2.3.1
Summary: This is a database of 300.000+ symbols containing Equities, ETFs, Funds, Indices, Currencies, Cryptocurrencies and Money Markets.
Home-page: https://www.jeroenbouma.com/
License: MIT
Author: Jeroen Bouma
Requires-Python: >=3.10,<3.14
Classifier: Development Status :: 5 - Production/Stable
Classifier: Intended Audience :: Financial and Insurance Industry
Classifier: License :: OSI Approved :: MIT License
Classifier: Operating System :: OS Independent
Classifier: Programming Language :: Python :: 3
Classifier: Programming Language :: Python :: 3.10
Classifier: Programming Language :: Python :: 3.11
Classifier: Programming Language :: Python :: 3.12
Classifier: Programming Language :: Python :: 3.13
Classifier: Topic :: Office/Business :: Financial :: Investment
Requires-Dist: financetoolkit (>=2.0.3,<3.0.0)
Requires-Dist: pandas[computation,excel,performance,plot] (>=2.2,<3.0)
Requires-Dist: requests (>=2.32.3,<3.0.0)
Requires-Dist: yfinance
Project-URL: Repository, https://github.com/JerBouma/FinanceDatabase
